correios/__init__.py
correios/correios.py
correios/package/__init__.py
correios/package/item.py
correios/package/package.py
correios_python_sdk-1.0.0.dist-info/DESCRIPTION.rst
correios_python_sdk-1.0.0.dist-info/METADATA
correios_python_sdk-1.0.0.dist-info/RECORD
correios_python_sdk-1.0.0.dist-info/WHEEL
correios_python_sdk-1.0.0.dist-info/metadata.json
correios_python_sdk-1.0.0.dist-info/top_level.txt
tests/__init__.py
tests/test_correios.py
tests/package/__init__.py
tests/package/test_item.py
tests/package/test_package.py
