Metadata-Version: 2.0
Name: correios-python-sdk
Version: 1.0.0
Summary: Correios's unofficial SDK for Python
Home-page: https://github.com/devsdmf/correios-python-sdk
Author: devsdmf
Author-email: devsdmf@gmail.com
License: MIT
Keywords: correios shipping sdk
Platform: UNKNOWN
Classifier: Development Status :: 5 - Production/Stable
Classifier: Intended Audience :: Developers
Classifier: Topic :: Software Development :: Libraries :: Python Modules
Classifier: License :: OSI Approved :: MIT License
Classifier: Operating System :: OS Independent
Classifier: Programming Language :: Python :: 3.3
Classifier: Programming Language :: Python :: 3.4
Classifier: Programming Language :: Python :: 3.5
Classifier: Programming Language :: Python :: 3.6
Requires-Dist: requests
